nua/agent/__init__.py
nua/agent/auto_install.py
nua/agent/detectors/__init__.py
nua/agent/detectors/base_detector.py
nua/agent/detectors/nodejs_yarn.py
nua/agent/detectors/python_source.py
nua/agent/detectors/python_wheels.py
nua/agent/scripts/__init__.py
nua/agent/scripts/app_builder.py
nua/agent/templates.py
nua/agent/version.py
nua_agent-0.5.43.dist-info/METADATA
nua_agent-0.5.43.dist-info/WHEEL
nua_agent-0.5.43.dist-info/entry_points.txt
nua_agent-0.5.43.dist-info/RECORD
