Metadata-Version: 2.1
Name: nua-agent
Version: 0.5.43
Summary: Nua agent
Home-page: https://github.com/abilian/nua
License: Apache-2.0
Author: Stefane Fermigier
Author-email: sf@abilian.com
Requires-Python: >=3.10,<4.0
Classifier: Development Status :: 3 - Alpha
Classifier: Environment :: Console
Classifier: Intended Audience :: Developers
Classifier: License :: OSI Approved :: Apache Software License
Classifier: Programming Language :: Python :: 3
Classifier: Programming Language :: Python :: 3.10
Classifier: Programming Language :: Python :: 3.11
Requires-Dist: nua-lib (==0.5.43)
Project-URL: Documentation, https://nua.rocks/
Project-URL: Repository, https://github.com/abilian/nua
